twoip/__init__.py
twoip/__version__.py
twoip/twoip.py
2ip-0.0.2.dist-info/LICENSE
2ip-0.0.2.dist-info/METADATA
2ip-0.0.2.dist-info/WHEEL
2ip-0.0.2.dist-info/top_level.txt
2ip-0.0.2.dist-info/RECORD
