Metadata-Version: 2.1
Name: 2ip
Version: 0.0.2
Summary: 2ip.me API Client.
Home-page: https://github.com/python-modules/2ip
Author: gbe0
Author-email: python@gbe0.com
License: MIT
Platform: UNKNOWN
Classifier: Intended Audience :: Developers
Classifier: Natural Language :: English
Classifier: License :: OSI Approved :: Apache Software License
Classifier: Programming Language :: Python
Classifier: Programming Language :: Python :: 3.6
Classifier: Programming Language :: Python :: 3.7
Classifier: Programming Language :: Python :: 3.8
Classifier: Programming Language :: Python :: 3.9
Requires-Python: >= 3.6
Requires-Dist: requests
